gage_inspect/__init__.py
gage_inspect/_util.py
gage_inspect/dataset/__init__.py
gage_inspect/dataset/_dataset.py
gage_inspect/dataset/_input.py
gage_inspect/dataset/_list.py
gage_inspect/dataset/_registry.py
gage_inspect/dataset/_yaml.py
gage_inspect/log/__init__.py
gage_inspect/log/_file.py
gage_inspect/log/_list.py
gage_inspect/patch.py
gage_inspect/sandbox/__init__.py
gage_inspect/sandbox/podman/cleanup.py
gage_inspect/sandbox/podman/compose.py
gage_inspect/sandbox/podman/config.py
gage_inspect/sandbox/podman/internal.py
gage_inspect/sandbox/podman/podman.py
gage_inspect/sandbox/podman/prereqs.py
gage_inspect/sandbox/podman/service.py
gage_inspect/sandbox/podman/util.py
gage_inspect/scorer/__init__.py
gage_inspect/scorer/_match.py
gage_inspect/scorer/_model.py
gage_inspect/solver/__init__.py
gage_inspect/solver/_task_doc.py
gage_inspect/solver/_template.py
gage_inspect/task/__init__.py
gage_inspect/task/_active.py
gage_inspect/task/_error.py
gage_inspect/task/_eval.py
gage_inspect/task/_list.py
gage_inspect/task/_run.py
gage_inspect/task/_task_doc.py
gage_inspect/task/_util.py
gage_inspect-0.2.1.dist-info/WHEEL
gage_inspect-0.2.1.dist-info/METADATA
gage_inspect-0.2.1.dist-info/RECORD
