Metadata-Version: 2.3
Name: gage-inspect
Version: 0.2.1
Summary: Gage support for Inspect AI
Classifier: License :: OSI Approved :: MIT License
Classifier: Development Status :: 3 - Alpha
Classifier: Programming Language :: Python
Classifier: Typing :: Typed
Classifier: Intended Audience :: Developers
Classifier: Intended Audience :: Science/Research
Classifier: Natural Language :: English
Requires-Dist: docstring-parser>=0.17.0
Requires-Dist: inspect-ai>=0.3.123
Requires-Dist: coverage>=7.12.0 ; extra == 'dev'
Requires-Dist: groktest>=0.3 ; extra == 'dev'
Requires-Dist: pytest>=8.4.1 ; extra == 'dev'
Requires-Dist: datasets>=4.4.1 ; extra == 'examples'
Requires-Dist: fastapi[standard]>=0.123.0 ; extra == 'examples'
Requires-Dist: gage-cli>=0.2.1 ; extra == 'examples'
Requires-Python: >=3.10
Provides-Extra: dev
Provides-Extra: examples
